{
  "agent_slug": "microsoft-365-administration-specialist",
  "release_version": "v0.1.0",
  "delivery_status": "validated",
  "human_verification": {
    "recorded": true,
    "reviewer": "commons-keeper",
    "verified_at": "2026-03-22"
  },
  "deployment_readiness": {
    "ready": true,
    "package_documented": true,
    "rollback_defined": true
  },
  "notes": [
    "validated evidence set is complete for issue #83 with source baseline, scenario coverage, release notes, and commercialization framing.",
    "No unreviewed regressions are present in evaluation artifacts for this package."
  ]
}
